casinotools/__init__.py
casinotools/casinotools.py
casinotools/tests.py
casinotools/fileformat/FileReaderWriterTools.py
casinotools/fileformat/Tags.py
casinotools/fileformat/__init__.py
casinotools/fileformat/test_FileReaderWriterTools.py
casinotools/fileformat/test_Tags.py
casinotools/fileformat/casino2/Composition.py
casinotools/fileformat/casino2/Element.py
casinotools/fileformat/casino2/ElementIntensity.py
casinotools/fileformat/casino2/File.py
casinotools/fileformat/casino2/GenerateSimFile.py
casinotools/fileformat/casino2/GraphData.py
casinotools/fileformat/casino2/MeanIonizationPotential.py
casinotools/fileformat/casino2/Region.py
casinotools/fileformat/casino2/RegionOptions.py
casinotools/fileformat/casino2/ScatteringEvent.py
casinotools/fileformat/casino2/SimulationData.py
casinotools/fileformat/casino2/SimulationOptions.py
casinotools/fileformat/casino2/SimulationResults.py
casinotools/fileformat/casino2/TrajectoriesData.py
casinotools/fileformat/casino2/Trajectory.py
casinotools/fileformat/casino2/Version.py
casinotools/fileformat/casino2/XrayRadial.py
casinotools/fileformat/casino2/XrayRadialReader.py
casinotools/fileformat/casino2/__init__.py
casinotools/fileformat/casino2/line.py
casinotools/fileformat/casino2/test_Composition.py
casinotools/fileformat/casino2/test_Element.py
casinotools/fileformat/casino2/test_ElementIntensity.py
casinotools/fileformat/casino2/test_File.py
casinotools/fileformat/casino2/test_GenerateSimFile.py
casinotools/fileformat/casino2/test_GraphData.py
casinotools/fileformat/casino2/test_MeanIonizationPotential.py
casinotools/fileformat/casino2/test_Region.py
casinotools/fileformat/casino2/test_RegionOptions.py
casinotools/fileformat/casino2/test_ScatteringEvent.py
casinotools/fileformat/casino2/test_SimulationData.py
casinotools/fileformat/casino2/test_SimulationOptions.py
casinotools/fileformat/casino2/test_SimulationResults.py
casinotools/fileformat/casino2/test_TrajectoriesData.py
pyCasinoTools-0.2.2.dist-info/DESCRIPTION.rst
pyCasinoTools-0.2.2.dist-info/METADATA
pyCasinoTools-0.2.2.dist-info/RECORD
pyCasinoTools-0.2.2.dist-info/WHEEL
pyCasinoTools-0.2.2.dist-info/metadata.json
pyCasinoTools-0.2.2.dist-info/top_level.txt
