Metadata-Version: 2.0
Name: pyCasinoTools
Version: 0.2.2
Summary: Python interface for the Monte Carlo simulation program CASINO version 2 and 3.
Home-page: https://github.com/drix00/casinotools
Author: Hendrix Demers
Author-email: hendrix.demers@mail.mcgill.ca
License: Apache Software License 2.0
Keywords: casinotools
Platform: UNKNOWN
Classifier: Development Status :: 4 - Beta
Classifier: Intended Audience :: Developers
Classifier: Intended Audience :: Science/Research
Classifier: License :: OSI Approved :: Apache Software License
Classifier: Natural Language :: English
Classifier: Programming Language :: Python
Classifier: Programming Language :: Python :: 2
Classifier: Programming Language :: Python :: 2.7
Classifier: Programming Language :: Python :: 3
Classifier: Programming Language :: Python :: 3.4
Classifier: Programming Language :: Python :: 3.5
Classifier: Programming Language :: Python :: 3.6
Classifier: Programming Language :: Python :: Implementation :: CPython
Classifier: Operating System :: OS Independent
Classifier: Topic :: Scientific/Engineering
Classifier: Topic :: Scientific/Engineering :: Physics
Requires-Dist: Pillow
Requires-Dist: numpy
